[{"id":"100000073","emis":"100000073","name":"BISHOPS SCHOOL OF SKILLS","status":"OPEN","sector":"PUBLIC","type":"SPECIAL NEEDS EDUCATION CENTRE","phase":"SCHOOL OF SKILLS","specialisation":"UNKNOWN","district":"METRO NORTH","circuit":"8","municipality":"CITY OF CAPE TOWN","suburb":"BISHOP LAVIS","township":"Bishop Lavis SP","town":"CITY OF CAPE TOWN","streetAddress":"KOPPIESDAMSTRAAT BISHOP LAVIS 7490, BISHOP LAVIS, CITY OF CAPE TOWN","postalAddress":"KOPPIESDAMSTRAAT CAPE TOWN UNKNOWN 7490","telephone":"0210100058","email":null,"principal":"H ISMAIEL","quintile":"UNKNOWN","noFee":"NO","section21":"YES","urbanRural":"URBAN","learners":308,"educators":18,"longitude":18.5825494291,"latitude":-33.9457996899,"isSpecialNeeds":true},{"id":"100000119","emis":"100000119","name":"OUDTSHOORN SCHOOL OF SKILLS","status":"OPEN","sector":"PUBLIC","type":"SPECIAL NEEDS EDUCATION CENTRE","phase":"SCHOOL OF SKILLS","specialisation":"UNKNOWN","district":"EDEN AND CENTRAL KAR","circuit":"5","municipality":"OUDTSHOORN","suburb":"OUDTSHOORN","township":"Oudtshoorn SP","town":"OUDTSHOORN","streetAddress":"LANGENHOVENWEG 104 OUDTSHOORN 6625, OUDTSHOORN, OUDTSHOORN","postalAddress":"104 LANGENHOVENWEG OUDTSHOORN UNKNOWN 6625","telephone":"0442726055","email":null,"principal":"RG BLOCK","quintile":"UNKNOWN","noFee":"NO","section21":"YES","urbanRural":"RURAL","learners":250,"educators":18,"longitude":22.2087604044,"latitude":-33.6023797382,"isSpecialNeeds":true},{"id":"100000291","emis":"100000291","name":"SNAP ACADEMY","status":"OPEN","sector":"INDEPENDENT","type":"SPECIAL NEEDS EDUCATION CENTRE","phase":"SPECIAL NEEDS EDUCATION","specialisation":"UNKNOWN","district":"METRO NORTH","circuit":"7","municipality":"CITY OF CAPE TOWN","suburb":"VIERLANDEN","township":"Vierlanden","town":"CITY OF CAPE TOWN","streetAddress":"9 DE DAM STREET DURBANVILLE 7550, VIERLANDEN, CITY OF CAPE TOWN","postalAddress":"9 DE DAM STREET DURBANVILLE UNKNOWN 7550","telephone":"0219757224","email":null,"principal":"S SMIT","quintile":null,"noFee":"NO","section21":"YES","urbanRural":"URBAN","learners":66,"educators":12,"longitude":18.6640195004,"latitude":-33.8097395651,"isSpecialNeeds":true},{"id":"100000323","emis":"100000323","name":"UP WITH DOWNS SCHOOL","status":"OPEN","sector":"INDEPENDENT","type":"SPECIAL NEEDS EDUCATION CENTRE","phase":"SPECIAL NEEDS EDUCATION","specialisation":"UNKNOWN","district":"EDEN AND CENTRAL KAR","circuit":"3","municipality":"GEORGE","suburb":"BLANCO","township":"Blanco","town":"GEORGE","streetAddress":"25 PIETER THERON STREET BLANCO 6529, BLANCO, GEORGE","postalAddress":"25 PIETER THERON STREET BLANCO UNKNOWN 6529","telephone":"0448708770","email":null,"principal":"SC STORBECK","quintile":null,"noFee":"NO","section21":"YES","urbanRural":"URBAN","learners":14,"educators":4,"longitude":22.4142081719,"latitude":-33.948297506,"isSpecialNeeds":true},{"id":"100000342","emis":"100000342","name":"VREDELUST COLLEGE","status":"OPEN","sector":"INDEPENDENT","type":"SPECIAL NEEDS EDUCATION CENTRE","phase":"SPECIAL NEEDS EDUCATION","specialisation":"UNKNOWN","district":"METRO NORTH","circuit":"6","municipality":"CITY OF CAPE TOWN","suburb":"VREDELUST BELLVILLE","township":"Vredelust","town":"CITY OF CAPE TOWN","streetAddress":"103 103 13TH AVENUE VREDELUST BELLVILLE 7530, VREDELUST BELLVILLE, CITY OF CAPE TOWN","postalAddress":"103 13TH AVENUE VREDELUST BELLVILLE 7530","telephone":"0219495526","email":null,"principal":"R KIRSTEN","quintile":null,"noFee":"NO","section21":"YES","urbanRural":"URBAN","learners":54,"educators":4,"longitude":18.6117158519,"latitude":-33.8934166298,"isSpecialNeeds":true},{"id":"100000430","emis":"100000430","name":"THE DREAMTREE SCHOOL","status":"OPEN","sector":"INDEPENDENT","type":"SPECIAL NEEDS EDUCATION CENTRE","phase":"SPECIAL NEEDS EDUCATION","specialisation":"UNKNOWN","district":"METRO EAST","circuit":"1","municipality":"STELLENBOSCH","suburb":"OUTSIDE A TOWN","township":null,"town":"OUTSIDE A TOWN","streetAddress":"SOMERSET COLLEGE CAMPUS BREDELL ROAD SOMERSET WEST 7129, OUTSIDE A TOWN, OUTSIDE A TOWN","postalAddress":"SOMERSET COLLEGE CAMPUS BREDELL ROAD SOMERSET WEST 7129","telephone":"0218422883","email":null,"principal":"E BRAND","quintile":null,"noFee":"NO","section21":"YES","urbanRural":"URBAN","learners":18,"educators":4,"longitude":18.8081095428,"latitude":-34.0409499526,"isSpecialNeeds":true},{"id":"100000436","emis":"100000436","name":"LANGERUGSKOOL","status":"OPEN","sector":"PUBLIC","type":"SPECIAL NEEDS EDUCATION CENTRE","phase":"SPECIAL NEEDS EDUCATION","specialisation":"UNKNOWN","district":"CAPE WINELANDS","circuit":"4","municipality":"BREEDE VALLEY","suburb":"WORCESTER","township":"Worcester SP1","town":"WORCESTER","streetAddress":"DISTILLERYWEG 8 WORCESTER 6850, WORCESTER, WORCESTER","postalAddress":"POSBUS 670 WORCESTER UNKNOWN 6849","telephone":"0233465300","email":null,"principal":"HC DE VILLIERS","quintile":"UNKNOWN","noFee":"NO","section21":"YES","urbanRural":"RURAL","learners":172,"educators":23,"longitude":19.4277490569,"latitude":-33.6491560219,"isSpecialNeeds":true},{"id":"100000561","emis":"100000561","name":"AMATHEMBA SCHOOL","status":"OPEN","sector":"INDEPENDENT","type":"SPECIAL NEEDS EDUCATION CENTRE","phase":"PRIMARY SCHOOL","specialisation":"UNKNOWN","district":"METRO NORTH","circuit":"9","municipality":"CITY OF CAPE TOWN","suburb":"PARKLANDS","township":"Parklands","town":"CITY OF CAPE TOWN","streetAddress":"3 FAIRBRIDGE ROAD TABLE VIEW 7441, PARKLANDS, CITY OF CAPE TOWN","postalAddress":"PO BOX 60385 TABLE VIEW UNKNOWN 7439","telephone":"0215563573","email":null,"principal":"K FERNANDEZ","quintile":null,"noFee":"NO","section21":"YES","urbanRural":"URBAN","learners":32,"educators":4,"longitude":18.4991799998,"latitude":-33.8067500005,"isSpecialNeeds":true},{"id":"100000592","emis":"100000592","name":"EDUEXCELLENCE PRIVATE REMEDIAL SCHOOL","status":"OPEN","sector":"INDEPENDENT","type":"SPECIAL NEEDS EDUCATION CENTRE","phase":"SPECIAL NEEDS EDUCATION","specialisation":"UNKNOWN","district":"METRO SOUTH","circuit":"9","municipality":"CITY OF CAPE TOWN","suburb":"NOORDHOEK","township":"Sunnydale","town":"OUTSIDE A TOWN","streetAddress":"1 CNR HOUMOED AVE & N/HOEK MAI NOORDHOEK 7975, NOORDHOEK, OUTSIDE A TOWN","postalAddress":"P O BOX 15 NOORDHOEK UNKNOWN 7979","telephone":"0217852992","email":null,"principal":"C J VOSS","quintile":null,"noFee":"NO","section21":"YES","urbanRural":"URBAN","learners":33,"educators":7,"longitude":18.3894291486,"latitude":-34.118439926,"isSpecialNeeds":true},{"id":"100000603","emis":"100000603","name":"LE BONHE'R COTTAGE SCHOOL","status":"OPEN","sector":"INDEPENDENT","type":"SPECIAL NEEDS EDUCATION CENTRE","phase":"PRIMARY SCHOOL","specialisation":"UNKNOWN","district":"EDEN AND CENTRAL KAR","circuit":"3","municipality":"GEORGE","suburb":"BERGSIG","township":"Loerie Par","town":"GEORGE","streetAddress":"55 STANDER STREET BERGSIG GEORGE 6539, BERGSIG, GEORGE","postalAddress":"55 STANDER STREET BERGSIG GEORGE 6539","telephone":"0792973397","email":null,"principal":"D BOTHA","quintile":null,"noFee":"NO","section21":"YES","urbanRural":"RURAL","learners":9,"educators":2,"longitude":22.486505547,"latitude":-33.959992606,"isSpecialNeeds":true},{"id":"100000619","emis":"100000619","name":"BLAAUWBERG RISE THERAPY AND LEARNING CE","status":"OPEN","sector":"INDEPENDENT","type":"SPECIAL NEEDS EDUCATION CENTRE","phase":"SPECIAL NEEDS EDUCATION","specialisation":"UNKNOWN","district":"METRO NORTH","circuit":"3","municipality":"CITY OF CAPE TOWN","suburb":"BLOUBERG RISE","township":"Blouberg R","town":"CITY OF CAPE TOWN","streetAddress":"7 RAVEN STREET BOUBERG RISE 7441, BLOUBERG RISE, CITY OF CAPE TOWN","postalAddress":"7 RAVEN STREET CAPE TOWN UNKNOWN 7441","telephone":"0215560931","email":null,"principal":"C WIESE","quintile":null,"noFee":"NO","section21":"YES","urbanRural":"RURAL","learners":43,"educators":5,"longitude":18.4834847535,"latitude":-33.8121586944,"isSpecialNeeds":true},{"id":"100000658","emis":"100000658","name":"DS DE WET SCHOOL FOR AUTISM","status":"OPEN","sector":"INDEPENDENT","type":"SPECIAL NEEDS EDUCATION CENTRE","phase":"SCHOOL OF SKILLS","specialisation":"UNKNOWN","district":"OVERBERG","circuit":"1","municipality":"CAPE AGULHAS","suburb":"BREDASDORP","township":"Bredasdorp","town":"BREDASDORP","streetAddress":"2 FIRLANE BREDASDORP 7280, BREDASDORP, BREDASDORP","postalAddress":"PO BOX 764 BREDASDORP UNKNOWN 7280","telephone":"0829294276","email":null,"principal":"CATHRIN JACOBS","quintile":null,"noFee":"NO","section21":"NO","urbanRural":"RURAL","learners":7,"educators":1,"longitude":20.0416750541,"latitude":-34.5303093081,"isSpecialNeeds":true},{"id":"100000668","emis":"100000668","name":"EDU-PLAY EARLY LEARNING CENTRE","status":"OPEN","sector":"INDEPENDENT","type":"SPECIAL NEEDS EDUCATION CENTRE","phase":"SPECIAL NEEDS EDUCATION","specialisation":"UNKNOWN","district":"METRO NORTH","circuit":"7","municipality":"CITY OF CAPE TOWN","suburb":"DURBANVILLE","township":"Durbanvill","town":"CITY OF CAPE TOWN","streetAddress":"144 MURRAY STREET VIERLANDEN KLEINHOEWES DURBANVILLE 7550, DURBANVILLE, CITY OF CAPE TOWN","postalAddress":"PO BOX 3724 TYGERVALLEY UNKNOWN 7536","telephone":"0219759991","email":null,"principal":"LM DU TOIT","quintile":null,"noFee":"NO","section21":"NO","urbanRural":"RURAL","learners":51,"educators":9,"longitude":18.6519494308,"latitude":-33.8328950157,"isSpecialNeeds":true},{"id":"100000728","emis":"100000728","name":"GRAAFWATER SPECIAL SCHOOL","status":"OPEN","sector":"PUBLIC","type":"SPECIAL NEEDS EDUCATION CENTRE","phase":"SPECIAL NEEDS EDUCATION","specialisation":"UNKNOWN","district":"WEST COAST","circuit":"4","municipality":"CEDERBERG","suburb":"GRAAFWATER","township":"Graaffwate","town":"GRAAFWATER","streetAddress":"C/O HOOF & VAN DER STEL STREET GRAAFWATER 8120, GRAAFWATER, GRAAFWATER","postalAddress":"PO BOX 4 GRAAFWATER UNKNOWN 8120","telephone":"0223000115","email":null,"principal":"R VAN ROOYEN","quintile":"UNKNOWN","noFee":"NO","section21":"NO","urbanRural":"URBAN","learners":229,"educators":17,"longitude":18.604335,"latitude":-32.154281,"isSpecialNeeds":true},{"id":"100000760","emis":"100000760","name":"POSITIVE BEHAVIOUR INTERVENTION AND RES","status":"OPEN","sector":"PUBLIC","type":"SPECIAL NEEDS EDUCATION CENTRE","phase":"SPECIAL NEEDS EDUCATION","specialisation":"UNKNOWN","district":"METRO SOUTH","circuit":"1","municipality":"CITY OF CAPE TOWN","suburb":"WYNBERG","township":"Wynberg","town":"CITY OF CAPE TOWN","streetAddress":"60 DURBAN ROAD 7800, WYNBERG, CITY OF CAPE TOWN","postalAddress":"60 DURBAN ROAD UNKNOWN 7800","telephone":"UNKNOWN","email":null,"principal":"M MAHADICK","quintile":"UNKNOWN","noFee":"NO","section21":"NO","urbanRural":"URBAN","learners":0,"educators":8,"longitude":18.464551,"latitude":-34.010411,"isSpecialNeeds":true},{"id":"100000762","emis":"100000762","name":"EARTHKIDO ONAFHANKLIKE SKOOL","status":"OPEN","sector":"INDEPENDENT","type":"SPECIAL NEEDS EDUCATION CENTRE","phase":"PRIMARY SCHOOL","specialisation":"UNKNOWN","district":"CAPE WINELANDS","circuit":"4","municipality":"BREEDE VALLEY","suburb":"VAN RIEBEECK PARK","township":"Van Riebee","town":"WORCESTER","streetAddress":"15 ST. ANDREWS CLOSE FAIRWAY HEIGHTS 6850, VAN RIEBEECK PARK, WORCESTER","postalAddress":"15 ST. ANDREWS CLOSE FAIRWAY HEIGHTS UNKNOWN 6850","telephone":"0233423034","email":null,"principal":"D ZEEMAN","quintile":null,"noFee":"NO","section21":"NO","urbanRural":"RURAL","learners":21,"educators":1,"longitude":19.444218,"latitude":-33.616153,"isSpecialNeeds":true},{"id":"100000772","emis":"100000772","name":"HERBERT STREET SPECIAL SCHOOL","status":"OPEN","sector":"PUBLIC","type":"SPECIAL NEEDS EDUCATION CENTRE","phase":"SPECIAL NEEDS EDUCATION","specialisation":"UNKNOWN","district":"METRO NORTH","circuit":"1","municipality":"CITY OF CAPE TOWN","suburb":"OAKDALE","township":"Sunkist","town":"CITY OF CAPE TOWN","streetAddress":"79 HERBERT STREET OAKDALE 7530, OAKDALE, CITY OF CAPE TOWN","postalAddress":"79 HERBERT STREET OAKDALE UNKNOWN 7530","telephone":"UNKNOWN","email":null,"principal":"Z HELM","quintile":"UNKNOWN","noFee":"NO","section21":"NO","urbanRural":"URBAN","learners":79,"educators":18,"longitude":18.639349,"latitude":-33.896693,"isSpecialNeeds":true},{"id":"100000774","emis":"100000774","name":"SILVERSTREAM SCHOOL OF SKILLS","status":"OPEN","sector":"PUBLIC","type":"SPECIAL NEEDS EDUCATION CENTRE","phase":"SCHOOL OF SKILLS","specialisation":"UNKNOWN","district":"METRO CENTRAL","circuit":"5","municipality":"CITY OF CAPE TOWN","suburb":"MANENBERG","township":"Manenberg","town":"CITY OF CAPE TOWN","streetAddress":"SONDEREND ROAD MANENBERG 7764, MANENBERG, CITY OF CAPE TOWN","postalAddress":"SONDEREND ROAD MANENBERG UNKNOWN 7764","telephone":"UNKNOWN","email":null,"principal":"L PIETERS","quintile":"UNKNOWN","noFee":"NO","section21":"NO","urbanRural":"URBAN","learners":226,"educators":20,"longitude":18.556669,"latitude":-33.985357,"isSpecialNeeds":true},{"id":"100000786","emis":"100000786","name":"EVERGREEN SPECIALISED EDUCATION CENTRE","status":"OPEN","sector":"INDEPENDENT","type":"SPECIAL NEEDS EDUCATION CENTRE","phase":"SPECIAL NEEDS EDUCATION","specialisation":"UNKNOWN","district":"CAPE WINELANDS","circuit":"6","municipality":"DRAKENSTEIN","suburb":"VRYKYK","township":"Vrykyk","town":"PAARL","streetAddress":"91 MAIN ROAD PAARL 7646, VRYKYK, PAARL","postalAddress":"91 MAIN ROAD PAARL UNKNOWN 7646","telephone":"UNKNOWN","email":null,"principal":"C MAREE","quintile":null,"noFee":"NO","section21":"NO","urbanRural":"RURAL","learners":17,"educators":1,"longitude":18.962796,"latitude":-33.756126,"isSpecialNeeds":true},{"id":"101007546","emis":"101007546","name":"DUNATOS PRIVATE SCHOOL TRUST OPERATING","status":"OPEN","sector":"INDEPENDENT","type":"SPECIAL NEEDS EDUCATION CENTRE","phase":"INTERMEDIATE SCHOOL","specialisation":"UNKNOWN","district":"METRO EAST","circuit":"3","municipality":"CITY OF CAPE TOWN","suburb":"STIKLAND HOSPITAAL","township":"Stikland Hospital","town":"CITY OF CAPE TOWN","streetAddress":"59 OLD PAARL ROAD STIKLAND ESTATE BELLVILLE 7530, STIKLAND HOSPITAAL, CITY OF CAPE TOWN","postalAddress":"YSTERHOUTSTRAAT 22 BLOMMENDAL BELLVILLE 7530","telephone":"0213006698","email":null,"principal":"S VAN ZYL","quintile":null,"noFee":"NO","section21":"YES","urbanRural":"RURAL","learners":242,"educators":38,"longitude":18.6539836752,"latitude":-33.8916226522,"isSpecialNeeds":true},{"id":"101301602","emis":"101301602","name":"CAREL DU TOIT SENTRUM","status":"OPEN","sector":"PUBLIC","type":"SPECIAL NEEDS EDUCATION CENTRE","phase":"SPECIAL NEEDS EDUCATION","specialisation":"UNKNOWN","district":"METRO NORTH","circuit":"1","municipality":"CITY OF CAPE TOWN","suburb":"TYGERBERG HOSPITAL","township":"Tygerberg Hospital","town":"CITY OF CAPE TOWN","streetAddress":"FRANCIE VAN ZIJLE DRIVE TYGERBERG HOSPITAL PAROW 7500, TYGERBERG HOSPITAL, CITY OF CAPE TOWN","postalAddress":"POSBUS 19130 TYGERBERG UNKNOWN 7505","telephone":"0219385312","email":null,"principal":"A HODGSON","quintile":"UNKNOWN","noFee":"NO","section21":"YES","urbanRural":"URBAN","learners":90,"educators":25,"longitude":18.6139483352,"latitude":-33.9147419431,"isSpecialNeeds":true},{"id":"101302204","emis":"101302204","name":"WESTCLIFF SPESIALE SKOOL","status":"OPEN","sector":"PUBLIC","type":"SPECIAL NEEDS EDUCATION CENTRE","phase":"SCHOOL OF SKILLS","specialisation":"UNKNOWN","district":"METRO EAST","circuit":"5","municipality":"CITY OF CAPE TOWN","suburb":"CHRISMAR","township":"Laurindale","town":"CITY OF CAPE TOWN","streetAddress":"OU PAARLWEG BELLVILLE 7532, CHRISMAR, CITY OF CAPE TOWN","postalAddress":"POSBUS 328 SANLAM HOF UNKNOWN 7532","telephone":"0219484877","email":null,"principal":"R LE SUEUR","quintile":"UNKNOWN","noFee":"NO","section21":"YES","urbanRural":"URBAN","learners":641,"educators":40,"longitude":18.6444606788,"latitude":-33.8980216675,"isSpecialNeeds":true},{"id":"101305604","emis":"101305604","name":"TYGERBERG HOSPITAALSKOOL","status":"OPEN","sector":"PUBLIC","type":"SPECIAL NEEDS EDUCATION CENTRE","phase":"HOSPITAL SCHOOL","specialisation":"UNKNOWN","district":"METRO NORTH","circuit":"1","municipality":"CITY OF CAPE TOWN","suburb":"TYGERBERG HOSPITAL","township":"Tygerberg Hospital","town":"CITY OF CAPE TOWN","streetAddress":"ADMIN GEBOU OOS HLG TYGERBERG HOSPITAAL TYGERBERG 7505, TYGERBERG HOSPITAL, CITY OF CAPE TOWN","postalAddress":"ADMIN GEBOU OOS HLG TYGERBERG HOSPITAAL TYGERBERG 7505","telephone":"0219385261","email":null,"principal":"Z HELM","quintile":"UNKNOWN","noFee":"NO","section21":"YES","urbanRural":"URBAN","learners":0,"educators":7,"longitude":18.6130096286,"latitude":-33.9104417573,"isSpecialNeeds":true},{"id":"101324612","emis":"101324612","name":"ATHLONE SKOOL VIR BLINDES","status":"OPEN","sector":"PUBLIC","type":"SPECIAL NEEDS EDUCATION CENTRE","phase":"SPECIAL NEEDS EDUCATION","specialisation":"UNKNOWN","district":"METRO NORTH","circuit":"6","municipality":"CITY OF CAPE TOWN","suburb":"GLENHAVEN","township":"Glenhaven","town":"CITY OF CAPE TOWN","streetAddress":"ATHLONESTRAAT GLENHAVEN BELLVILLE SUID 7533, GLENHAVEN, CITY OF CAPE TOWN","postalAddress":"PRIVAATSAK X1 KASSELSVLEI UNKNOWN 7533","telephone":"0219512234","email":null,"principal":"J PHILANDER","quintile":"UNKNOWN","noFee":"NO","section21":"YES","urbanRural":"URBAN","learners":288,"educators":39,"longitude":18.6536169564,"latitude":-33.9174923936,"isSpecialNeeds":true},{"id":"101324639","emis":"101324639","name":"OASIS SPECIAL SCHOOL","status":"OPEN","sector":"PUBLIC","type":"SPECIAL NEEDS EDUCATION CENTRE","phase":"SPECIAL NEEDS EDUCATION","specialisation":"UNKNOWN","district":"METRO NORTH","circuit":"5","municipality":"CITY OF CAPE TOWN","suburb":"BELHAR EXT 8","township":"Belhar 8","town":"CITY OF CAPE TOWN","streetAddress":"CARMEN CLOSE BELHAR 7493, BELHAR EXT 8, CITY OF CAPE TOWN","postalAddress":"POSBUS 10091 BELHAR UNKNOWN 7507","telephone":"0219522100","email":null,"principal":"SG REED","quintile":"UNKNOWN","noFee":"NO","section21":"YES","urbanRural":"URBAN","learners":284,"educators":24,"longitude":18.6367182081,"latitude":-33.9410349869,"isSpecialNeeds":true},{"id":"101324795","emis":"101324795","name":"FLORIDA VAARDIGHEIDSKOOL","status":"OPEN","sector":"PUBLIC","type":"SPECIAL NEEDS EDUCATION CENTRE","phase":"SCHOOL OF SKILLS","specialisation":"UNKNOWN","district":"METRO NORTH","circuit":"3","municipality":"CITY OF CAPE TOWN","suburb":"RUYTERWACHT","township":"Ruyterwacht","town":"CITY OF CAPE TOWN","streetAddress":"H/V RICHMOND EN TEXELSTRAAT RUYTERWACHT 7475, RUYTERWACHT, CITY OF CAPE TOWN","postalAddress":"POSBUS 850 EPPING INDUSTRIA RUYTERWACHT 7475","telephone":"0215350756","email":null,"principal":"TN ANDREWS","quintile":"UNKNOWN","noFee":"YES","section21":"YES","urbanRural":"URBAN","learners":305,"educators":17,"longitude":18.5534373536,"latitude":-33.9227924328,"isSpecialNeeds":true},{"id":"101328529","emis":"101328529","name":"CHERE  BOTHA SKOOL","status":"OPEN","sector":"PUBLIC","type":"SPECIAL NEEDS EDUCATION CENTRE","phase":"SPECIAL NEEDS EDUCATION","specialisation":"UNKNOWN","district":"METRO EAST","circuit":"7","municipality":"CITY OF CAPE TOWN","suburb":"OAKDALE","township":"Oakglen","town":"CITY OF CAPE TOWN","streetAddress":"20 MEERLUST STREET OAK GLEN BELLVILLE 7530, OAKDALE, CITY OF CAPE TOWN","postalAddress":"20 MEERLUST STREET OAK GLEN BELLVILLE 7530","telephone":"0219105300","email":null,"principal":"J.L. VAN DER WESTHUIZEN","quintile":"UNKNOWN","noFee":"NO","section21":"YES","urbanRural":"URBAN","learners":313,"educators":31,"longitude":18.664421407,"latitude":-33.88702293,"isSpecialNeeds":true},{"id":"102316490","emis":"102316490","name":"ST. JOSEPH'S SCHOOL","status":"OPEN","sector":"PUBLIC","type":"SPECIAL NEEDS EDUCATION CENTRE","phase":"SPECIAL NEEDS EDUCATION","specialisation":"UNKNOWN","district":"METRO CENTRAL","circuit":"3","municipality":"CITY OF CAPE TOWN","suburb":"MONTEVIDEO","township":"Montevideo SP2","town":"CITY OF CAPE TOWN","streetAddress":"PALLOTTIWEG 40 MONTANA 7490, MONTEVIDEO, CITY OF CAPE TOWN","postalAddress":"P.O.BOX 21131 DURRHEIM UNKNOWN 7491","telephone":"0219351369","email":null,"principal":"G PETERSEN","quintile":"UNKNOWN","noFee":"NO","section21":"YES","urbanRural":"URBAN","learners":210,"educators":18,"longitude":18.5738082636,"latitude":-33.9639884892,"isSpecialNeeds":true},{"id":"102484636","emis":"102484636","name":"FILIA SKOOL","status":"OPEN","sector":"PUBLIC","type":"SPECIAL NEEDS EDUCATION CENTRE","phase":"SPECIAL NEEDS EDUCATION","specialisation":"UNKNOWN","district":"METRO NORTH","circuit":"2","municipality":"CITY OF CAPE TOWN","suburb":"VASCO ESTATE","township":"Vasco Estate","town":"CITY OF CAPE TOWN","streetAddress":"MILTONWEG 107 VRIJZEE,GOODWOOD 7460, VASCO ESTATE, CITY OF CAPE TOWN","postalAddress":"POSBUS 12911 N1 CITY UNKNOWN 7463","telephone":"0215921361","email":null,"principal":"MM SAAYMAN","quintile":"UNKNOWN","noFee":"NO","section21":"YES","urbanRural":"URBAN","learners":233,"educators":21,"longitude":18.5615294356,"latitude":-33.9012103524,"isSpecialNeeds":true},{"id":"102484679","emis":"102484679","name":"ASTRA SKOOL","status":"OPEN","sector":"PUBLIC","type":"SPECIAL NEEDS EDUCATION CENTRE","phase":"SPECIAL NEEDS EDUCATION","specialisation":"UNKNOWN","district":"METRO CENTRAL","circuit":"3","municipality":"CITY OF CAPE TOWN","suburb":"MONTEVIDEO","township":"Montevideo SP2","town":"CITY OF CAPE TOWN","streetAddress":"PALOTTIWEG MONTANA 7490, MONTEVIDEO, CITY OF CAPE TOWN","postalAddress":"POSBUS 21106 DURRHEIM UNKNOWN 7491","telephone":"0219340155","email":null,"principal":"M. MABOTHA","quintile":"UNKNOWN","noFee":"NO","section21":"YES","urbanRural":"URBAN","learners":147,"educators":19,"longitude":18.5752491927,"latitude":-33.9631065528,"isSpecialNeeds":true},{"id":"103000129","emis":"103000129","name":"NOMPUMELELO SKOOL","status":"OPEN","sector":"PUBLIC","type":"SPECIAL NEEDS EDUCATION CENTRE","phase":"SPECIAL NEEDS EDUCATION","specialisation":"UNKNOWN","district":"METRO CENTRAL","circuit":"7","municipality":"CITY OF CAPE TOWN","suburb":"GUGULETU","township":"Gugulethu SP","town":"CITY OF CAPE TOWN","streetAddress":"ST.GABRIELS STREET GUGULETHU 7750, GUGULETU, CITY OF CAPE TOWN","postalAddress":"P O BOX 507 GATESVILLE UNKNOWN 7766","telephone":"0216378062","email":null,"principal":"M TUBENI","quintile":"UNKNOWN","noFee":"NO","section21":"YES","urbanRural":"URBAN","learners":323,"educators":24,"longitude":18.5678749606,"latitude":-33.9794755133,"isSpecialNeeds":true},{"id":"103007340","emis":"103007340","name":"THEMBALITSHA FOUNDATION TRADING AS SCHO","status":"OPEN","sector":"INDEPENDENT","type":"SPECIAL NEEDS EDUCATION CENTRE","phase":"SPECIAL NEEDS EDUCATION","specialisation":"UNKNOWN","district":"METRO CENTRAL","circuit":"9","municipality":"CITY OF CAPE TOWN","suburb":"OBSERVATORY","township":"Observator","town":"CITY OF CAPE TOWN","streetAddress":"23 KOTZEE ROAD OBSERVATORY MOWBRAY 7725, OBSERVATORY, CITY OF CAPE TOWN","postalAddress":"27 WAVERLEY BUSINESS PARK 23 KOTZEE ROAD OBSERVATORY 7925","telephone":"0214470334","email":null,"principal":"P W LEWIS","quintile":null,"noFee":"YES","section21":"YES","urbanRural":"RURAL","learners":173,"educators":13,"longitude":18.4726906336,"latitude":-33.9432977284,"isSpecialNeeds":true},{"id":"103008027","emis":"103008027","name":"SEAL COLLEGE","status":"OPEN","sector":"INDEPENDENT","type":"SPECIAL NEEDS EDUCATION CENTRE","phase":"SECONDARY SCHOOL","specialisation":"UNKNOWN","district":"METRO NORTH","circuit":"9","municipality":"CITY OF CAPE TOWN","suburb":"MILNERTON","township":"Milnerton SP","town":"CITY OF CAPE TOWN","streetAddress":"9 OXALIS STREET MILNERTON 7441, MILNERTON, CITY OF CAPE TOWN","postalAddress":"9 OXALIS STREET MILNERTON UNKNOWN 7441","telephone":"0215552732","email":null,"principal":"C. VAN HEERDEN","quintile":null,"noFee":"NO","section21":"YES","urbanRural":"RURAL","learners":14,"educators":1,"longitude":18.5040822487,"latitude":-33.8642637764,"isSpecialNeeds":true},{"id":"103008185","emis":"103008185","name":"LEARN TO LIVE SCHOOL OF SKILLS","status":"OPEN","sector":"INDEPENDENT","type":"SPECIAL NEEDS EDUCATION CENTRE","phase":"SCHOOL OF SKILLS","specialisation":"UNKNOWN","district":"METRO CENTRAL","circuit":"3","municipality":"CITY OF CAPE TOWN","suburb":"CAPE TOWN CITY CENTRE","township":"De Waterkant","town":"CITY OF CAPE TOWN","streetAddress":"2 SOMERSET ROAD GREENPOINT, CAPE TOWN 8001, CAPE TOWN CITY CENTRE, CITY OF CAPE TOWN","postalAddress":"2 SOMERSET ROAD GREENPOINT CAPE TOWN 8001","telephone":"0214216764","email":null,"principal":"A AUSTEN","quintile":null,"noFee":"YES","section21":"YES","urbanRural":"RURAL","learners":203,"educators":13,"longitude":18.4188540466,"latitude":-33.9161652214,"isSpecialNeeds":true},{"id":"103008402","emis":"103008402","name":"SHELANTI PRIVATE REMEDIAL SCHOOL","status":"OPEN","sector":"INDEPENDENT","type":"SPECIAL NEEDS EDUCATION CENTRE","phase":"SPECIAL NEEDS EDUCATION","specialisation":"UNKNOWN","district":"METRO NORTH","circuit":"9","municipality":"CITY OF CAPE TOWN","suburb":"PARKLANDS","township":"Cape Metro NU1","town":"CITY OF CAPE TOWN","streetAddress":"24 STEPNEY ROAD PARKLANDS 7441, PARKLANDS, CITY OF CAPE TOWN","postalAddress":"14 CHARLES HOFFE MELKBOSSTRAND UNKNOWN 7441","telephone":"0215573484","email":null,"principal":"D KEMPEN","quintile":null,"noFee":"NO","section21":"YES","urbanRural":"RURAL","learners":88,"educators":13,"longitude":18.5158682864,"latitude":-33.8038559374,"isSpecialNeeds":true},{"id":"103302201","emis":"103302201","name":"DE GRENDEL SPESIALE SKOOL","status":"OPEN","sector":"PUBLIC","type":"SPECIAL NEEDS EDUCATION CENTRE","phase":"SCHOOL OF SKILLS","specialisation":"UNKNOWN","district":"METRO NORTH","circuit":"9","municipality":"CITY OF CAPE TOWN","suburb":"TIJGERHOF","township":"Tijgerhof","town":"CITY OF CAPE TOWN","streetAddress":"NOBLEWEG (VANAF KOEBERGWEG) MILNERTON 7441, TIJGERHOF, CITY OF CAPE TOWN","postalAddress":"PRIVAATSAK X2 MILNERTON UNKNOWN 7435","telephone":"0215523010","email":null,"principal":"C.A SMITH","quintile":"UNKNOWN","noFee":"NO","section21":"YES","urbanRural":"URBAN","learners":445,"educators":32,"longitude":18.4997792956,"latitude":-33.8818006742,"isSpecialNeeds":true},{"id":"103305600","emis":"103305600","name":"GROOTE SCHUUR HOSPITAAL SKOOL","status":"OPEN","sector":"PUBLIC","type":"SPECIAL NEEDS EDUCATION CENTRE","phase":"HOSPITAL SCHOOL","specialisation":"UNKNOWN","district":"METRO CENTRAL","circuit":"9","municipality":"CITY OF CAPE TOWN","suburb":"OBSERVATORY","township":"Observatory","town":"CITY OF CAPE TOWN","streetAddress":"E11 NUWE GSH HOSPITAALLAAN OBSERVATORY 7925, OBSERVATORY, CITY OF CAPE TOWN","postalAddress":"P/A E11 SUPERINTENDENTSKANTOOR NUWE GROOTE SCHUUR-HOSPITAAL OBSERVATORY 7925","telephone":"0214045012","email":null,"principal":"R.W. CUPIDO","quintile":"UNKNOWN","noFee":"NO","section21":"YES","urbanRural":"URBAN","learners":0,"educators":2,"longitude":18.4630689785,"latitude":-33.9407709889,"isSpecialNeeds":true},{"id":"103305603","emis":"103305603","name":"RED CROSS CHILDREN'S HOSPITAL","status":"OPEN","sector":"PUBLIC","type":"SPECIAL NEEDS EDUCATION CENTRE","phase":"HOSPITAL SCHOOL","specialisation":"UNKNOWN","district":"METRO CENTRAL","circuit":"10","municipality":"CITY OF CAPE TOWN","suburb":"RONDEBOSCH","township":"Rondebosch","town":"CITY OF CAPE TOWN","streetAddress":"KLIPFONTEIN RD RONDEBOSCH 7700, RONDEBOSCH, CITY OF CAPE TOWN","postalAddress":"KLIPFONTEIN RD RONDEBOSCH UNKNOWN 7700","telephone":"UNKNOWN","email":null,"principal":"M SHARGEY","quintile":"UNKNOWN","noFee":"NO","section21":"YES","urbanRural":"URBAN","learners":0,"educators":5,"longitude":18.4883130372,"latitude":-33.9548361835,"isSpecialNeeds":true},{"id":"103315605","emis":"103315605","name":"SEVEN STEPS ACADEMY FOR THE DEAF","status":"OPEN","sector":"PUBLIC","type":"SPECIAL NEEDS EDUCATION CENTRE","phase":"SPECIAL NEEDS EDUCATION","specialisation":"UNKNOWN","district":"METRO CENTRAL","circuit":"5","municipality":"CITY OF CAPE TOWN","suburb":"HOUT BAY","township":"Zonnebloem","town":"CITY OF CAPE TOWN","streetAddress":"200 CONSTITUTION STREET ZONNEBLOEM CAPE TOWN 7925, HOUT BAY, CITY OF CAPE TOWN","postalAddress":"P.O. BOX 2986 CAPE TOWN UNKNOWN 8000","telephone":"0217901052","email":null,"principal":"L KANNEMEYER","quintile":"UNKNOWN","noFee":"NO","section21":"YES","urbanRural":"URBAN","learners":null,"educators":22,"longitude":18.434263,"latitude":-33.93358,"isSpecialNeeds":true},{"id":"103315608","emis":"103315608","name":"MOLENBEEK SKOOL","status":"OPEN","sector":"PUBLIC","type":"SPECIAL NEEDS EDUCATION CENTRE","phase":"SPECIAL NEEDS EDUCATION","specialisation":"UNKNOWN","district":"METRO CENTRAL","circuit":"4","municipality":"CITY OF CAPE TOWN","suburb":"MAITLAND GARDEN VILLAGE","township":"Maitland Garden Village","town":"CITY OF CAPE TOWN","streetAddress":"ALEXANDRA AND ANNEX ROAD MAITLAND 7404, MAITLAND GARDEN VILLAGE, CITY OF CAPE TOWN","postalAddress":"PO BOX 953 MAITLAND UNKNOWN 7404","telephone":"0215114507","email":null,"principal":"AM WARNICK","quintile":"UNKNOWN","noFee":"NO","section21":"YES","urbanRural":"URBAN","learners":169,"educators":16,"longitude":18.485562632,"latitude":-33.9301438433,"isSpecialNeeds":true},{"id":"103484644","emis":"103484644","name":"ALPHA SKOOL","status":"OPEN","sector":"PUBLIC","type":"SPECIAL NEEDS EDUCATION CENTRE","phase":"SPECIAL NEEDS EDUCATION","specialisation":"UNKNOWN","district":"METRO CENTRAL","circuit":"9","municipality":"CITY OF CAPE TOWN","suburb":"WOODSTOCK","township":"Woodstock","town":"CITY OF CAPE TOWN","streetAddress":"84 PALMERSTON ROAD WOODSTOCK 7925, WOODSTOCK, CITY OF CAPE TOWN","postalAddress":"POSBUS 48 CAPE TOWN UNKNOWN 7915","telephone":"0214471213","email":null,"principal":"N. KEARNS","quintile":"UNKNOWN","noFee":"NO","section21":"YES","urbanRural":"URBAN","learners":110,"educators":15,"longitude":18.4508858999,"latitude":-33.9354059149,"isSpecialNeeds":true},{"id":"104314706","emis":"104314706","name":"OCEAN VIEW SKOOL","status":"OPEN","sector":"PUBLIC","type":"SPECIAL NEEDS EDUCATION CENTRE","phase":"SPECIAL NEEDS EDUCATION","specialisation":"UNKNOWN","district":"METRO SOUTH","circuit":"6","municipality":"CITY OF CAPE TOWN","suburb":"OCEAN VIEW","township":"Ocean View","town":"CITY OF CAPE TOWN","streetAddress":"C/O DRACO ROAD AND CASTOR WAY OCEAN VIEW 7975, OCEAN VIEW, CITY OF CAPE TOWN","postalAddress":"PO BOX 43847 FISH HOEK UNKNOWN 7974","telephone":"0217832381","email":null,"principal":"AR ROSSOUW","quintile":"UNKNOWN","noFee":"NO","section21":"YES","urbanRural":"URBAN","learners":107,"educators":8,"longitude":18.3495287294,"latitude":-34.1457702932,"isSpecialNeeds":true},{"id":"105007171","emis":"105007171","name":"KHANYISA SCHOOL","status":"OPEN","sector":"INDEPENDENT","type":"SPECIAL NEEDS EDUCATION CENTRE","phase":"PRIMARY SCHOOL","specialisation":"UNKNOWN","district":"METRO SOUTH","circuit":"8","municipality":"CITY OF CAPE TOWN","suburb":"PLUMSTEAD","township":"Plumstead","town":"CITY OF CAPE TOWN","streetAddress":"4 VICTORIA ROAD PLUMSTEAD 7801, PLUMSTEAD, CITY OF CAPE TOWN","postalAddress":"P O BOX 476 PLUMSTEAD UNKNOWN 7801","telephone":"0217611709","email":null,"principal":"L SCHIPPER","quintile":null,"noFee":"NO","section21":"YES","urbanRural":"RURAL","learners":60,"educators":7,"longitude":18.4682503931,"latitude":-34.0243325069,"isSpecialNeeds":true},{"id":"105302200","emis":"105302200","name":"BATAVIA SPESIALE SKOOL","status":"OPEN","sector":"PUBLIC","type":"SPECIAL NEEDS EDUCATION CENTRE","phase":"SCHOOL OF SKILLS","specialisation":"UNKNOWN","district":"METRO CENTRAL","circuit":"10","municipality":"CITY OF CAPE TOWN","suburb":"CLAREMONT","township":"Claremont","town":"CITY OF CAPE TOWN","streetAddress":"LAURIERWEG CLAREMONT 7708, CLAREMONT, CITY OF CAPE TOWN","postalAddress":"POSBUS 36357 GLOSDERRY CAPE TOWN 7702","telephone":"0216715110","email":null,"principal":"S THIART","quintile":"UNKNOWN","noFee":"NO","section21":"YES","urbanRural":"URBAN","learners":515,"educators":36,"longitude":18.4898095221,"latitude":-33.9832543345,"isSpecialNeeds":true},{"id":"105308363","emis":"105308363","name":"OAKLEY HOUSE SCHOOL","status":"OPEN","sector":"INDEPENDENT","type":"SPECIAL NEEDS EDUCATION CENTRE","phase":"SPECIAL NEEDS EDUCATION","specialisation":"UNKNOWN","district":"METRO SOUTH","circuit":"7","municipality":"CITY OF CAPE TOWN","suburb":"DIEPRIVER","township":"Diep River","town":"CITY OF CAPE TOWN","streetAddress":"68 MYBURGH ROAD DIEPRIVER 7800, DIEPRIVER, CITY OF CAPE TOWN","postalAddress":"68 MYBURGH ROAD DIEP RIVER UNKNOWN 7800","telephone":"0217133885","email":null,"principal":"JA BUCHANAN","quintile":null,"noFee":"NO","section21":"YES","urbanRural":"RURAL","learners":214,"educators":41,"longitude":18.4621407219,"latitude":-34.0346123706,"isSpecialNeeds":true},{"id":"105309608","emis":"105309608","name":"MARY KIHN SCHOOL","status":"OPEN","sector":"PUBLIC","type":"SPECIAL NEEDS EDUCATION CENTRE","phase":"SPECIAL NEEDS EDUCATION","specialisation":"UNKNOWN","district":"METRO CENTRAL","circuit":"5","municipality":"CITY OF CAPE TOWN","suburb":"OBSERVATORY","township":"Observatory","town":"CITY OF CAPE TOWN","streetAddress":"34 LOW STREET OBSERVATORY 7925, OBSERVATORY, CITY OF CAPE TOWN","postalAddress":"34 LOW STREET OBSERVATORY UNKNOWN 7925","telephone":"0214470310","email":null,"principal":"J WILMOT","quintile":"UNKNOWN","noFee":"NO","section21":"YES","urbanRural":"URBAN","learners":107,"educators":19,"longitude":18.4750734567,"latitude":-33.9413068184,"isSpecialNeeds":true},{"id":"105314196","emis":"105314196","name":"BLOUVLEI SKOOL","status":"OPEN","sector":"PUBLIC","type":"SPECIAL NEEDS EDUCATION CENTRE","phase":"SPECIAL NEEDS EDUCATION","specialisation":"UNKNOWN","district":"METRO SOUTH","circuit":"8","municipality":"CITY OF CAPE TOWN","suburb":"RETREAT","township":"Retreat","town":"CITY OF CAPE TOWN","streetAddress":"6DE LAAN 89 RETREAT 7945, RETREAT, CITY OF CAPE TOWN","postalAddress":"POSBUS 124 CAPE TOWN UNKNOWN 7965","telephone":"0217120857","email":null,"principal":"CA DAVIDS","quintile":"UNKNOWN","noFee":"NO","section21":"YES","urbanRural":"URBAN","learners":195,"educators":14,"longitude":18.4735651519,"latitude":-34.0600281515,"isSpecialNeeds":true},{"id":"105314387","emis":"105314387","name":"CAFDA SCHOOL OF SKILLS","status":"OPEN","sector":"PUBLIC","type":"SPECIAL NEEDS EDUCATION CENTRE","phase":"SCHOOL OF SKILLS","specialisation":"UNKNOWN","district":"METRO SOUTH","circuit":"2","municipality":"CITY OF CAPE TOWN","suburb":"RETREAT","township":"Cafda Village","town":"CITY OF CAPE TOWN","streetAddress":"PETER CHARLES STREET RETREAT 7945, RETREAT, CITY OF CAPE TOWN","postalAddress":"PETER CHARLES STREET RETREAT UNKNOWN 7945","telephone":"0217129182","email":null,"principal":"A MANUELS","quintile":"UNKNOWN","noFee":"NO","section21":"YES","urbanRural":"URBAN","learners":341,"educators":21,"longitude":18.4875235721,"latitude":-34.0569125205,"isSpecialNeeds":true},{"id":"105314633","emis":"105314633","name":"DOMINIKAANSE SKOOL VIR DOWES","status":"OPEN","sector":"PUBLIC","type":"SPECIAL NEEDS EDUCATION CENTRE","phase":"SPECIAL NEEDS EDUCATION","specialisation":"UNKNOWN","district":"METRO SOUTH","circuit":"3","municipality":"CITY OF CAPE TOWN","suburb":"WYNBERG","township":"Wynberg","town":"CITY OF CAPE TOWN","streetAddress":"CLARE ROAD WITTEBOME 7800, WYNBERG, CITY OF CAPE TOWN","postalAddress":"POSBUS 19027 WYNBERG UNKNOWN 7824","telephone":"0217618046","email":null,"principal":"HC ARENZ","quintile":"UNKNOWN","noFee":"NO","section21":"YES","urbanRural":"URBAN","learners":236,"educators":39,"longitude":18.4723564358,"latitude":-34.0145745148,"isSpecialNeeds":true},{"id":"105315036","emis":"105315036","name":"MAITLAND COTTAGE HOME","status":"OPEN","sector":"PUBLIC","type":"SPECIAL NEEDS EDUCATION CENTRE","phase":"HOSPITAL SCHOOL","specialisation":"UNKNOWN","district":"METRO CENTRAL","circuit":"9","municipality":"CITY OF CAPE TOWN","suburb":"NEWLANDS","township":"Newlands","town":"CITY OF CAPE TOWN","streetAddress":"KILDAREWEG NUWELAND 7700, NEWLANDS, CITY OF CAPE TOWN","postalAddress":"KILDAREWEG NUWELAND UNKNOWN 7700","telephone":"0216742090","email":null,"principal":"L.B. JANTJIES","quintile":"UNKNOWN","noFee":"NO","section21":"YES","urbanRural":"URBAN","learners":0,"educators":3,"longitude":18.4561702284,"latitude":-33.9747442634,"isSpecialNeeds":true},{"id":"105315601","emis":"105315601","name":"BEL PORTO SKOOL","status":"OPEN","sector":"PUBLIC","type":"SPECIAL NEEDS EDUCATION CENTRE","phase":"SPECIAL NEEDS EDUCATION","specialisation":"UNKNOWN","district":"METRO CENTRAL","circuit":"6","municipality":"CITY OF CAPE TOWN","suburb":"LANSDOWNE","township":"Lansdowne","town":"CITY OF CAPE TOWN","streetAddress":"2 ARCADIA AVENUE LANSDOWNE 7780, LANSDOWNE, CITY OF CAPE TOWN","postalAddress":"PRIVAATSAK X3 CLAREINCH UNKNOWN 7740","telephone":"0216964134","email":null,"principal":"I HERMAN","quintile":"UNKNOWN","noFee":"NO","section21":"YES","urbanRural":"URBAN","learners":248,"educators":23,"longitude":18.4931981901,"latitude":-33.9875772924,"isSpecialNeeds":true},{"id":"105315606","emis":"105315606","name":"GLENBRIDGE SPECIAL SCHOOL","status":"OPEN","sector":"PUBLIC","type":"SPECIAL NEEDS EDUCATION CENTRE","phase":"SPECIAL NEEDS EDUCATION","specialisation":"UNKNOWN","district":"METRO SOUTH","circuit":"5","municipality":"CITY OF CAPE TOWN","suburb":"DIEPRIVER","township":"Diep River","town":"CITY OF CAPE TOWN","streetAddress":"91 MAIN ROAD DIEP RIVER 7800, DIEPRIVER, CITY OF CAPE TOWN","postalAddress":"P.O. BOX 30055 TOKAI UNKNOWN 7966","telephone":"0217122075","email":null,"principal":"R VAN ROOYEN","quintile":"UNKNOWN","noFee":"NO","section21":"YES","urbanRural":"URBAN","learners":242,"educators":31,"longitude":18.4658523244,"latitude":-34.0342976945,"isSpecialNeeds":true},{"id":"105315611","emis":"105315611","name":"TAFELBERGSKOOL","status":"OPEN","sector":"PUBLIC","type":"SPECIAL NEEDS EDUCATION CENTRE","phase":"SPECIAL NEEDS EDUCATION","specialisation":"UNKNOWN","district":"METRO NORTH","circuit":"7","municipality":"CITY OF CAPE TOWN","suburb":"BOTHASIG","township":"Bothasig (Milnerton)","town":"CITY OF CAPE TOWN","streetAddress":"2 SWELLENGREBEL AVENUE BOTHASIG 7441, BOTHASIG, CITY OF CAPE TOWN","postalAddress":"POSBUS 28376 BOTHASIG UNKNOWN 7406","telephone":"0215582405","email":null,"principal":"L.E BENECKE","quintile":"UNKNOWN","noFee":"NO","section21":"YES","urbanRural":"URBAN","learners":372,"educators":36,"longitude":18.5430028235,"latitude":-33.8571636273,"isSpecialNeeds":true},{"id":"105315612","emis":"105315612","name":"VERA-SCHOOL","status":"OPEN","sector":"PUBLIC","type":"SPECIAL NEEDS EDUCATION CENTRE","phase":"SPECIAL NEEDS EDUCATION","specialisation":"UNKNOWN","district":"METRO CENTRAL","circuit":"6","municipality":"CITY OF CAPE TOWN","suburb":"RONDEBOSCH EAST","township":"Rondebosch East","town":"CITY OF CAPE TOWN","streetAddress":"20 ANGLESEY ROAD RONDEBOSCH-EAST 7700, RONDEBOSCH EAST, CITY OF CAPE TOWN","postalAddress":"PRIVATE BAG X4 CLAREINCH UNKNOWN 7740","telephone":"0216962844","email":null,"principal":"CD REED","quintile":"UNKNOWN","noFee":"NO","section21":"YES","urbanRural":"URBAN","learners":182,"educators":25,"longitude":18.4946786489,"latitude":-33.9791759107,"isSpecialNeeds":true},{"id":"105315613","emis":"105315613","name":"VISTA NOVA-SCHOOL","status":"OPEN","sector":"PUBLIC","type":"SPECIAL NEEDS EDUCATION CENTRE","phase":"SPECIAL NEEDS EDUCATION","specialisation":"UNKNOWN","district":"METRO CENTRAL","circuit":"10","municipality":"CITY OF CAPE TOWN","suburb":"RONDEBOSCH","township":"Rondebosch","town":"CITY OF CAPE TOWN","streetAddress":"11 MILNER ROAD RONDEBOSCH 7700, RONDEBOSCH, CITY OF CAPE TOWN","postalAddress":"P.O. BOX 193 RONDEBOSCH UNKNOWN 7700","telephone":"0216895323","email":null,"principal":"R WARD","quintile":"UNKNOWN","noFee":"NO","section21":"YES","urbanRural":"URBAN","learners":445,"educators":45,"longitude":18.4861778734,"latitude":-33.9569787998,"isSpecialNeeds":true},{"id":"105447900","emis":"105447900","name":"OTTERY JEUGSORG EN ONDERWYSSENTRUM","status":"OPEN","sector":"PUBLIC","type":"SPECIAL NEEDS EDUCATION CENTRE","phase":"SPECIAL NEEDS EDUCATION","specialisation":"UNKNOWN","district":"METRO SOUTH","circuit":"1","municipality":"CITY OF CAPE TOWN","suburb":"OTTERY","township":"Ferness","town":"CITY OF CAPE TOWN","streetAddress":"PLANTASIEWEG 175 OTTERY 7808, OTTERY, CITY OF CAPE TOWN","postalAddress":"PRIVAATSAK X4 CAPE TOWN UNKNOWN 7808","telephone":"0217033030","email":null,"principal":"M. MAHADICK","quintile":"UNKNOWN","noFee":"NO","section21":"YES","urbanRural":"URBAN","learners":0,"educators":15,"longitude":18.4993885163,"latitude":-34.0189385134,"isSpecialNeeds":true},{"id":"105484628","emis":"105484628","name":"MARY HARDING SKOOL","status":"OPEN","sector":"PUBLIC","type":"SPECIAL NEEDS EDUCATION CENTRE","phase":"SPECIAL NEEDS EDUCATION","specialisation":"UNKNOWN","district":"METRO CENTRAL","circuit":"7","municipality":"CITY OF CAPE TOWN","suburb":"BELGRAVIA","township":"Belgravia(Athlone)","town":"CITY OF CAPE TOWN","streetAddress":"KLIPFONTEINWEG ATHLONE 7760, BELGRAVIA, CITY OF CAPE TOWN","postalAddress":"POSBUS 104 ATHLONE UNKNOWN 7764","telephone":"0216378068","email":null,"principal":"K FLORIS","quintile":"UNKNOWN","noFee":"NO","section21":"YES","urbanRural":"URBAN","learners":312,"educators":27,"longitude":18.5238976628,"latitude":-33.9667014368,"isSpecialNeeds":true},{"id":"105484652","emis":"105484652","name":"EROSSKOOL","status":"OPEN","sector":"PUBLIC","type":"SPECIAL NEEDS EDUCATION CENTRE","phase":"SPECIAL NEEDS EDUCATION","specialisation":"UNKNOWN","district":"METRO CENTRAL","circuit":"4","municipality":"CITY OF CAPE TOWN","suburb":"BRIDGETOWN","township":"Bridgetown","town":"CITY OF CAPE TOWN","streetAddress":"TARENTAALWEG BRIDGETOWN ATHLONE 7764, BRIDGETOWN, CITY OF CAPE TOWN","postalAddress":"POSBUS 82 ATHLONE UNKNOWN 7764","telephone":"0216379080","email":null,"principal":"S JULIUS","quintile":"UNKNOWN","noFee":"NO","section21":"YES","urbanRural":"URBAN","learners":327,"educators":50,"longitude":18.5300615951,"latitude":-33.9525689551,"isSpecialNeeds":true},{"id":"106000108","emis":"106000108","name":"NOLUTHANDO SCHOOL FOR THE DEAF","status":"OPEN","sector":"PUBLIC","type":"SPECIAL NEEDS EDUCATION CENTRE","phase":"SPECIAL NEEDS EDUCATION","specialisation":"UNKNOWN","district":"METRO EAST","circuit":"6","municipality":"CITY OF CAPE TOWN","suburb":"KHAYELITSHA","township":"Trevor Vilakazi","town":"CITY OF CAPE TOWN","streetAddress":"400 JAPHTA MASEMOLA SITE-B KHAYELITSHA 7784, KHAYELITSHA, CITY OF CAPE TOWN","postalAddress":"P.O.BOX 129 KHAYELITSHA UNKNOWN 7783","telephone":"0213611160","email":null,"principal":"A.A. NCINANE","quintile":"UNKNOWN","noFee":"NO","section21":"YES","urbanRural":"URBAN","learners":294,"educators":48,"longitude":18.6753454658,"latitude":-34.0242004198,"isSpecialNeeds":true},{"id":"106000113","emis":"106000113","name":"TEMBALETU","status":"OPEN","sector":"PUBLIC","type":"SPECIAL NEEDS EDUCATION CENTRE","phase":"SPECIAL NEEDS EDUCATION","specialisation":"UNKNOWN","district":"METRO CENTRAL","circuit":"8","municipality":"CITY OF CAPE TOWN","suburb":"GUGULETU","township":"Gugulethu SP","town":"CITY OF CAPE TOWN","streetAddress":"NY 77 GUGULETHU 7750, GUGULETU, CITY OF CAPE TOWN","postalAddress":"PO BOX 2228 CLAREINCH UNKNOWN 7740","telephone":"0216375902","email":null,"principal":"AB MTSHAZO","quintile":"UNKNOWN","noFee":"YES","section21":"YES","urbanRural":"URBAN","learners":192,"educators":21,"longitude":18.5703870997,"latitude":-33.9892232062,"isSpecialNeeds":true},{"id":"106008227","emis":"106008227","name":"MITCHELL'S PLAIN SCHOOL OF SKILLS","status":"OPEN","sector":"PUBLIC","type":"SPECIAL NEEDS EDUCATION CENTRE","phase":"SCHOOL OF SKILLS","specialisation":"UNKNOWN","district":"METRO SOUTH","circuit":"7","municipality":"CITY OF CAPE TOWN","suburb":"ROCKLANDS","township":"Rocklands","town":"CITY OF CAPE TOWN","streetAddress":"C/O WELTEVREDEN & CEDARS AVE ROCKLANDS MITCHELLS PLAIN 7785, ROCKLANDS, CITY OF CAPE TOWN","postalAddress":"CO WELTEVREDEN & CEDARS AVE ROCKLANDS MITCHELL'S PLAIN 7785","telephone":"0213921213","email":null,"principal":"N. J MEYER","quintile":"UNKNOWN","noFee":"NO","section21":"YES","urbanRural":"URBAN","learners":608,"educators":37,"longitude":18.5973406859,"latitude":-34.06148138,"isSpecialNeeds":true},{"id":"106008228","emis":"106008228","name":"SIVIWE SCHOOL OF SKILLS","status":"OPEN","sector":"PUBLIC","type":"SPECIAL NEEDS EDUCATION CENTRE","phase":"SCHOOL OF SKILLS","specialisation":"UNKNOWN","district":"METRO CENTRAL","circuit":"8","municipality":"CITY OF CAPE TOWN","suburb":"GUGULETU","township":"Gugulethu SP","town":"CITY OF CAPE TOWN","streetAddress":"NY 82 GUGULETHU 7750, GUGULETU, CITY OF CAPE TOWN","postalAddress":"P O BOX 53 GUGLETHU UNKNOWN 7750","telephone":"0216332958","email":null,"principal":"Y LUPONDO","quintile":"UNKNOWN","noFee":"NO","section21":"YES","urbanRural":"URBAN","learners":570,"educators":31,"longitude":18.5698274039,"latitude":-33.9911962122,"isSpecialNeeds":true},{"id":"106008368","emis":"106008368","name":"LATHI-THA SCHOOL OF SKILLS","status":"OPEN","sector":"PUBLIC","type":"SPECIAL NEEDS EDUCATION CENTRE","phase":"SCHOOL OF SKILLS","specialisation":"UNKNOWN","district":"METRO EAST","circuit":"7","municipality":"CITY OF CAPE TOWN","suburb":"KHAYELITSHA","township":"Village V1 North","town":"CITY OF CAPE TOWN","streetAddress":"16 MKHONTO CRESCENT E-SECTION KHAYELITSHA 7784, KHAYELITSHA, CITY OF CAPE TOWN","postalAddress":"PO BOX 90 KHAYELITSHA UNKNOWN 7784","telephone":"0815216666","email":null,"principal":"MJ WITBOOI","quintile":"UNKNOWN","noFee":"NO","section21":"YES","urbanRural":"RURAL","learners":462,"educators":27,"longitude":18.6640713878,"latitude":-34.0362266822,"isSpecialNeeds":true},{"id":"106324531","emis":"106324531","name":"KHAYELITSHA LSEN SCHOOL","status":"OPEN","sector":"PUBLIC","type":"SPECIAL NEEDS EDUCATION CENTRE","phase":"SPECIAL NEEDS EDUCATION","specialisation":"UNKNOWN","district":"METRO EAST","circuit":"1","municipality":"CITY OF CAPE TOWN","suburb":"KHAYELITSHA","township":"Village V1 North","town":"CITY OF CAPE TOWN","streetAddress":"MSAKABENI ROAD 7784, KHAYELITSHA, CITY OF CAPE TOWN","postalAddress":"P.O.BOX 231 MITCHELLSPLAIN UNKNOWN 7784","telephone":"0740741239","email":null,"principal":"B.F. VELEBAYI","quintile":"UNKNOWN","noFee":"NO","section21":"YES","urbanRural":"URBAN","learners":410,"educators":31,"longitude":18.6600329974,"latitude":-34.039332752,"isSpecialNeeds":true},{"id":"106494615","emis":"106494615","name":"LENTEGEUR SCHOOL FOR LSEN-SMH","status":"OPEN","sector":"PUBLIC","type":"SPECIAL NEEDS EDUCATION CENTRE","phase":"SPECIAL NEEDS EDUCATION","specialisation":"UNKNOWN","district":"METRO SOUTH","circuit":"4","municipality":"CITY OF CAPE TOWN","suburb":"LENTEGEUR","township":"Lentegeur","town":"CITY OF CAPE TOWN","streetAddress":"LENTEGEUR HOSPITAL HIGHLANDS DRIVE MITCHELLS PLAIN 7785, LENTEGEUR, CITY OF CAPE TOWN","postalAddress":"POSBUS 80 MITCHELL'S PLAIN UNKNOWN 7785","telephone":"0213714111","email":null,"principal":"E DAVIDS","quintile":"UNKNOWN","noFee":"NO","section21":"YES","urbanRural":"URBAN","learners":230,"educators":24,"longitude":18.6219506206,"latitude":-34.0231039821,"isSpecialNeeds":true},{"id":"106494623","emis":"106494623","name":"BEACON SKOOL","status":"OPEN","sector":"PUBLIC","type":"SPECIAL NEEDS EDUCATION CENTRE","phase":"SPECIAL NEEDS EDUCATION","specialisation":"UNKNOWN","district":"METRO SOUTH","circuit":"7","municipality":"CITY OF CAPE TOWN","suburb":"WESTRIDGE","township":"Westridge(Mitchells Plain)","town":"CITY OF CAPE TOWN","streetAddress":"LOGANBERRYWEG WESTRIDGE MITCHELLS PLAIN 7785, WESTRIDGE, CITY OF CAPE TOWN","postalAddress":"POSBUS 346 TOWN CENTRE MITCHELL'S PLAIN 7789","telephone":"0213714324","email":null,"principal":"C MULLER","quintile":"UNKNOWN","noFee":"NO","section21":"YES","urbanRural":"URBAN","learners":275,"educators":27,"longitude":18.5977335334,"latitude":-34.0520996061,"isSpecialNeeds":true},{"id":"106494631","emis":"106494631","name":"AGAPESKOOL","status":"OPEN","sector":"PUBLIC","type":"SPECIAL NEEDS EDUCATION CENTRE","phase":"SPECIAL NEEDS EDUCATION","specialisation":"UNKNOWN","district":"METRO SOUTH","circuit":"1","municipality":"CITY OF CAPE TOWN","suburb":"TAFELSIG","township":"Tafelsig","town":"CITY OF CAPE TOWN","streetAddress":"16 YELLOWWOOD ROAD TAFELSIG MITCHELLS PLAIN 7785, TAFELSIG, CITY OF CAPE TOWN","postalAddress":"POSBUS 223 MITCHELL'S PLAIN UNKNOWN 7785","telephone":"0213924162","email":null,"principal":"B. LAMBERT","quintile":"UNKNOWN","noFee":"NO","section21":"YES","urbanRural":"URBAN","learners":192,"educators":21,"longitude":18.6234102117,"latitude":-34.0637713186,"isSpecialNeeds":true},{"id":"107008381","emis":"107008381","name":"AXIOS SCHOOL OF SKILLS","status":"OPEN","sector":"PUBLIC","type":"SPECIAL NEEDS EDUCATION CENTRE","phase":"SCHOOL OF SKILLS","specialisation":"UNKNOWN","district":"METRO EAST","circuit":"1","municipality":"CITY OF CAPE TOWN","suburb":"EERSTERIVIER SOUTH","township":"Blue Downs SP2","town":"CITY OF CAPE TOWN","streetAddress":"OLD FAURE ROAD FAURE 7103, EERSTERIVIER SOUTH, CITY OF CAPE TOWN","postalAddress":"PO BOX 731 CAPE TOWN UNKNOWN 7103","telephone":"0219045306","email":null,"principal":"G.V ENGELBRECHT","quintile":"UNKNOWN","noFee":"NO","section21":"YES","urbanRural":"URBAN","learners":413,"educators":26,"longitude":18.7233885325,"latitude":-34.0211423576,"isSpecialNeeds":true},{"id":"107315600","emis":"107315600","name":"ALTA DU TOIT SKOOL","status":"OPEN","sector":"PUBLIC","type":"SPECIAL NEEDS EDUCATION CENTRE","phase":"SPECIAL NEEDS EDUCATION","specialisation":"UNKNOWN","district":"METRO EAST","circuit":"4","municipality":"CITY OF CAPE TOWN","suburb":"AMANDELSIG","township":"Rouxville","town":"CITY OF CAPE TOWN","streetAddress":"PIET FRANSMANSTRAAT 37 KUILSRIVIER 7580, AMANDELSIG, CITY OF CAPE TOWN","postalAddress":"PRIVAATSAK X10 KUILSRIVIER UNKNOWN 7579","telephone":"0219034178","email":null,"principal":"M ERASMUS","quintile":"UNKNOWN","noFee":"NO","section21":"YES","urbanRural":"URBAN","learners":371,"educators":30,"longitude":18.6980921697,"latitude":-33.9253232232,"isSpecialNeeds":true},{"id":"107315607","emis":"107315607","name":"JAN KRIEL-SKOOL","status":"OPEN","sector":"PUBLIC","type":"SPECIAL NEEDS EDUCATION CENTRE","phase":"SPECIAL NEEDS EDUCATION","specialisation":"UNKNOWN","district":"METRO EAST","circuit":"3","municipality":"CITY OF CAPE TOWN","suburb":"JAN KRIEL","township":"Elim","town":"CITY OF CAPE TOWN","streetAddress":"SKOOLSTRAAT KUILSRIVIER 7580, JAN KRIEL, CITY OF CAPE TOWN","postalAddress":"POSBUS 17 KUILSRIVIER UNKNOWN 7579","telephone":"0219031108","email":null,"principal":"GB ODENDAAL","quintile":"UNKNOWN","noFee":"NO","section21":"YES","urbanRural":"URBAN","learners":523,"educators":53,"longitude":18.6836835175,"latitude":-33.9202630736,"isSpecialNeeds":true},{"id":"107315609","emis":"107315609","name":"PAARL-SKOOL VIR NEURAAL GESTREMDE KINDE","status":"OPEN","sector":"PUBLIC","type":"SPECIAL NEEDS EDUCATION CENTRE","phase":"SPECIAL NEEDS EDUCATION","specialisation":"UNKNOWN","district":"METRO EAST","circuit":"2","municipality":"CITY OF CAPE TOWN","suburb":"MORGENSTER HEIGHTS","township":"Arauna","town":"CITY OF CAPE TOWN","streetAddress":"ROGLANDSTRAAT BRACKENFELL 7560, MORGENSTER HEIGHTS, CITY OF CAPE TOWN","postalAddress":"POSBUS 140 BRACKENFELL UNKNOWN 7561","telephone":"0219815555","email":null,"principal":"JNC KRUGER","quintile":"UNKNOWN","noFee":"NO","section21":"YES","urbanRural":"URBAN","learners":315,"educators":39,"longitude":18.689184407,"latitude":-33.8677608454,"isSpecialNeeds":true},{"id":"107324647","emis":"107324647","name":"BET-EL SKOOL VIR EPILEPTICI","status":"OPEN","sector":"PUBLIC","type":"SPECIAL NEEDS EDUCATION CENTRE","phase":"SPECIAL NEEDS EDUCATION","specialisation":"UNKNOWN","district":"METRO EAST","circuit":"1","municipality":"CITY OF CAPE TOWN","suburb":"KUILSRIVIER SOUTH SMALLHOLDING","township":"Kalkfontein 1","town":"CITY OF CAPE TOWN","streetAddress":"UIT OU NOOIENSFONTEINPAD KUILSRIVIER 7580, KUILSRIVIER SOUTH SMALLHOLDING, CITY OF CAPE TOWN","postalAddress":"POSBUS 105 CAPE TOWN UNKNOWN 7580","telephone":"0219035147","email":null,"principal":"T NEFDT","quintile":"UNKNOWN","noFee":"NO","section21":"YES","urbanRural":"URBAN","learners":406,"educators":24,"longitude":18.6620598428,"latitude":-33.9500391773,"isSpecialNeeds":true},{"id":"108447870","emis":"108447870","name":"PAARL VAARDIGHEIDSKOOL","status":"OPEN","sector":"PUBLIC","type":"SPECIAL NEEDS EDUCATION CENTRE","phase":"SCHOOL OF SKILLS","specialisation":"UNKNOWN","district":"CAPE WINELANDS","circuit":"9","municipality":"DRAKENSTEIN","suburb":"OUTSIDE A TOWN","township":"Drakenstein NU","town":"OUTSIDE A TOWN","streetAddress":"R45 FRANSCHHOEK ROAD SIMONDIUM 7624, OUTSIDE A TOWN, OUTSIDE A TOWN","postalAddress":"POSBUS X6004 SUIDER-PAARL UNKNOWN 7624","telephone":"0218632043","email":null,"principal":"S MATIWANE","quintile":"UNKNOWN","noFee":"YES","section21":"YES","urbanRural":"RURAL","learners":366,"educators":20,"longitude":18.9560219875,"latitude":-33.7862611741,"isSpecialNeeds":true},{"id":"108474126","emis":"108474126","name":"LIGSTRAAL SKOOL","status":"OPEN","sector":"PUBLIC","type":"SPECIAL NEEDS EDUCATION CENTRE","phase":"SPECIAL NEEDS EDUCATION","specialisation":"UNKNOWN","district":"CAPE WINELANDS","circuit":"9","municipality":"DRAKENSTEIN","suburb":"LANGVLEI","township":"Amstelhof","town":"PAARL","streetAddress":"PIENAARSTRAAT 60 PAARL-OOS 7627, LANGVLEI, PAARL","postalAddress":"POSBUS 1102 NEDERBURG PAARL-OOS 7627","telephone":"0218627182","email":null,"principal":"IR MENTOOR","quintile":"UNKNOWN","noFee":"NO","section21":"YES","urbanRural":"RURAL","learners":270,"educators":22,"longitude":18.9982284499,"latitude":-33.7384183019,"isSpecialNeeds":true},{"id":"109329754","emis":"109329754","name":"DOROTHEA SPESIALE SKOOL","status":"OPEN","sector":"PUBLIC","type":"SPECIAL NEEDS EDUCATION CENTRE","phase":"SPECIAL NEEDS EDUCATION","specialisation":"UNKNOWN","district":"CAPE WINELANDS","circuit":"10","municipality":"STELLENBOSCH","suburb":"CLOETESVILLE","township":"Cloetesville SP","town":"STELLENBOSCH","streetAddress":"H/V LANG- EN LASTSTRAAT CLOETESVILLE 7600, CLOETESVILLE, STELLENBOSCH","postalAddress":"POSBUS 2046 MATIELAND STELLENBOSCH 7600","telephone":"0218895461","email":null,"principal":"A. WILLIAMS","quintile":"UNKNOWN","noFee":"NO","section21":"YES","urbanRural":"RURAL","learners":256,"educators":24,"longitude":18.8536681356,"latitude":-33.9096858007,"isSpecialNeeds":true},{"id":"110324159","emis":"110324159","name":"RUSTHOF SKOOL","status":"OPEN","sector":"PUBLIC","type":"SPECIAL NEEDS EDUCATION CENTRE","phase":"SPECIAL NEEDS EDUCATION","specialisation":"UNKNOWN","district":"METRO EAST","circuit":"8","municipality":"CITY OF CAPE TOWN","suburb":"STRAND","township":"Onverwacht","town":"CITY OF CAPE TOWN","streetAddress":"CNR BROADWAY BOULEVARD & ONVERWACHT STREET STRAND 7140, STRAND, CITY OF CAPE TOWN","postalAddress":"POSBUS 514 SOMERSET-WES UNKNOWN 7129","telephone":"0218514441","email":null,"principal":"M MALLY","quintile":"UNKNOWN","noFee":"NO","section21":"YES","urbanRural":"URBAN","learners":280,"educators":30,"longitude":18.8476352014,"latitude":-34.1235175647,"isSpecialNeeds":true},{"id":"111007560","emis":"111007560","name":"GLORIA BOTHA SCHOOL STRAND","status":"OPEN","sector":"INDEPENDENT","type":"SPECIAL NEEDS EDUCATION CENTRE","phase":"SPECIAL NEEDS EDUCATION","specialisation":"UNKNOWN","district":"METRO EAST","circuit":"1","municipality":"CITY OF CAPE TOWN","suburb":"VICTORIA PARK","township":"Victoria Park","town":"CITY OF CAPE TOWN","streetAddress":"2 SARATOGA CRESCENT SOMERSET WEST 7130, VICTORIA PARK, CITY OF CAPE TOWN","postalAddress":"2 SARATOGA CRESCENT VICTORIA PART SOMERSET WEST 7130","telephone":"0218512156","email":null,"principal":"T DAWSON","quintile":null,"noFee":"NO","section21":"YES","urbanRural":"RURAL","learners":43,"educators":4,"longitude":18.8296332002,"latitude":-34.0927287901,"isSpecialNeeds":true},{"id":"112447811","emis":"112447811","name":"WELLINGTON SCHOOL OF SKILLS","status":"OPEN","sector":"PUBLIC","type":"SPECIAL NEEDS EDUCATION CENTRE","phase":"SCHOOL OF SKILLS","specialisation":"UNKNOWN","district":"CAPE WINELANDS","circuit":"7","municipality":"DRAKENSTEIN","suburb":"HILLCREST","township":"Hillcrest","town":"WELLINGTON","streetAddress":"H/V MALVA- EN CHAMPAGNESTRAAT WELLINGTON 7655, HILLCREST, WELLINGTON","postalAddress":"PRIVAATSAK X10 WELLINGTON UNKNOWN 7654","telephone":"0218731068","email":null,"principal":"BG CUPIDO","quintile":"UNKNOWN","noFee":"NO","section21":"YES","urbanRural":"RURAL","learners":467,"educators":29,"longitude":18.9967767705,"latitude":-33.6503021489,"isSpecialNeeds":true},{"id":"113008387","emis":"113008387","name":"AGULHAS SCHOOL OF SKILLS","status":"OPEN","sector":"PUBLIC","type":"SPECIAL NEEDS EDUCATION CENTRE","phase":"SCHOOL OF SKILLS","specialisation":"UNKNOWN","district":"OVERBERG","circuit":"1","municipality":"CAPE AGULHAS","suburb":"NAPIER","township":"Napier SP","town":"NAPIER","streetAddress":"STEYNSTRAAT NAPIER 7270, NAPIER, NAPIER","postalAddress":"PO BOX 17 NAPIER UNKNOWN 7270","telephone":"0284233902","email":null,"principal":"E DE VILLIERS","quintile":"UNKNOWN","noFee":"NO","section21":"YES","urbanRural":"RURAL","learners":334,"educators":18,"longitude":19.8973627433,"latitude":-34.4787003796,"isSpecialNeeds":true},{"id":"113334642","emis":"113334642","name":"MISPAH-SKOOL","status":"OPEN","sector":"PUBLIC","type":"SPECIAL NEEDS EDUCATION CENTRE","phase":"SPECIAL NEEDS EDUCATION","specialisation":"UNKNOWN","district":"OVERBERG","circuit":"1","municipality":"CAPE AGULHAS","suburb":"ELIM","township":"Elim SP","town":"CAPE AGULHAS RURAL","streetAddress":"KERKSTRAAT 1A ELIM 7284, ELIM, CAPE AGULHAS RURAL","postalAddress":"POSBUS 13 ELIM UNKNOWN 7284","telephone":"0284821810","email":null,"principal":"M.C. OCTOBER","quintile":"UNKNOWN","noFee":"NO","section21":"YES","urbanRural":"RURAL","learners":106,"educators":8,"longitude":19.7589646275,"latitude":-34.5961029631,"isSpecialNeeds":true},{"id":"115001202","emis":"115001202","name":"CAMPHILL SCHOOL","status":"OPEN","sector":"INDEPENDENT","type":"SPECIAL NEEDS EDUCATION CENTRE","phase":"SPECIAL NEEDS EDUCATION","specialisation":"UNKNOWN","district":"OVERBERG","circuit":"2","municipality":"OVERSTRAND","suburb":"OUTSIDE A TOWN","township":"Overstrand NU","town":"OUTSIDE A TOWN","streetAddress":"CALEDON ROAD HEMEL EN AARDE, HERMANUS 7200, OUTSIDE A TOWN, OUTSIDE A TOWN","postalAddress":"PO BOX 68 HERMANUS UNKNOWN 7200","telephone":"0283124949","email":null,"principal":"J BOTHA","quintile":null,"noFee":"NO","section21":"YES","urbanRural":"RURAL","learners":56,"educators":6,"longitude":19.2261203053,"latitude":-34.385618155,"isSpecialNeeds":true},{"id":"118102203","emis":"118102203","name":"VAN KERVEL SPESIALE SKOOL","status":"OPEN","sector":"PUBLIC","type":"SPECIAL NEEDS EDUCATION CENTRE","phase":"SCHOOL OF SKILLS","specialisation":"UNKNOWN","district":"EDEN AND CENTRAL KAR","circuit":"3","municipality":"GEORGE","suburb":"EASTERN EXT","township":"Eastern Ext","town":"GEORGE","streetAddress":"MEYERSTRAAT GEORGE-OOS 6529, EASTERN EXT, GEORGE","postalAddress":"PRIVAATSAK X6601 GEORGE-OOS UNKNOWN 6539","telephone":"0448742042","email":null,"principal":"HJ KOEGELENBERG","quintile":"UNKNOWN","noFee":"NO","section21":"YES","urbanRural":"RURAL","learners":528,"educators":33,"longitude":22.4763798116,"latitude":-33.9574956413,"isSpecialNeeds":true},{"id":"118447846","emis":"118447846","name":"OLYMPIA SKOOL","status":"OPEN","sector":"PUBLIC","type":"SPECIAL NEEDS EDUCATION CENTRE","phase":"SCHOOL OF SKILLS","specialisation":"UNKNOWN","district":"EDEN AND CENTRAL KAR","circuit":"3","municipality":"GEORGE","suburb":"DEVILLE PARK","township":"Deville Park","town":"GEORGE","streetAddress":"OLYMPICRYLAAN DELLVILLE PARK PACALTSDORP 6534, DEVILLE PARK, GEORGE","postalAddress":"PRIVAATSAK X7004 PACALTSDORP UNKNOWN 6534","telephone":"0448780357","email":null,"principal":"G HAUPT","quintile":"UNKNOWN","noFee":"NO","section21":"YES","urbanRural":"RURAL","learners":508,"educators":29,"longitude":22.4330779037,"latitude":-34.0090018887,"isSpecialNeeds":true},{"id":"118456233","emis":"118456233","name":"CARPE DIEM SKOOL","status":"OPEN","sector":"PUBLIC","type":"SPECIAL NEEDS EDUCATION CENTRE","phase":"SPECIAL NEEDS EDUCATION","specialisation":"UNKNOWN","district":"EDEN AND CENTRAL KAR","circuit":"8","municipality":"GEORGE","suburb":"BOS EN DAL","township":"Groeneweid Park","town":"GEORGE","streetAddress":"LANGSTRAAT GEORGE 6529, BOS EN DAL, GEORGE","postalAddress":"PRIVAATSAK X6576 GEORGE UNKNOWN 6530","telephone":"0448744074","email":null,"principal":"E GROBLER","quintile":"UNKNOWN","noFee":"NO","section21":"YES","urbanRural":"RURAL","learners":378,"educators":38,"longitude":22.4489096212,"latitude":-33.9779303075,"isSpecialNeeds":true},{"id":"124447889","emis":"124447889","name":"ELJADA-KAIROS SKOOL","status":"OPEN","sector":"PUBLIC","type":"SPECIAL NEEDS EDUCATION CENTRE","phase":"SPECIAL NEEDS EDUCATION","specialisation":"UNKNOWN","district":"EDEN AND CENTRAL KAR","circuit":"5","municipality":"OUDTSHOORN","suburb":"OUDTSHOORN","township":"Oudtshoorn SP","town":"OUDTSHOORN","streetAddress":"BARON VAN REEDESTRAAT 25 25 OUDTSHOORN 6620, OUDTSHOORN, OUDTSHOORN","postalAddress":"PRIVAATSAK X642 OUDTSHOORN UNKNOWN 6620","telephone":"0442037600","email":null,"principal":"H.J. BAARTMAN","quintile":"UNKNOWN","noFee":"NO","section21":"YES","urbanRural":"RURAL","learners":276,"educators":23,"longitude":22.2028436802,"latitude":-33.5895510431,"isSpecialNeeds":true},{"id":"129333050","emis":"129333050","name":"STEINTHAL SEKONDﾊR","status":"OPEN","sector":"PUBLIC","type":"SPECIAL NEEDS EDUCATION CENTRE","phase":"SCHOOL OF SKILLS","specialisation":"UNKNOWN","district":"CAPE WINELANDS","circuit":"6","municipality":"WITZENBERG","suburb":"OUTSIDE A TOWN","township":"Witzenberg NU","town":"OUTSIDE A TOWN","streetAddress":"STEINTHALLANDGOED TULBAGH 6820, OUTSIDE A TOWN, OUTSIDE A TOWN","postalAddress":"PRIVAATSAK 4 TULBAGH UNKNOWN 6820","telephone":"0230220084","email":null,"principal":"W.J.A SAVILLE","quintile":"UNKNOWN","noFee":"YES","section21":"YES","urbanRural":"RURAL","learners":404,"educators":20,"longitude":19.1858100008,"latitude":-33.2794675149,"isSpecialNeeds":true},{"id":"130315604","emis":"130315604","name":"DE LA BAT-SKOOL","status":"OPEN","sector":"PUBLIC","type":"SPECIAL NEEDS EDUCATION CENTRE","phase":"SPECIAL NEEDS EDUCATION","specialisation":"UNKNOWN","district":"CAPE WINELANDS","circuit":"4","municipality":"BREEDE VALLEY","suburb":"REUNION PARK","township":"Reunion Park","town":"WORCESTER","streetAddress":"DE LA BATWEG 30 WORCESTER 6850, REUNION PARK, WORCESTER","postalAddress":"POSBUS 98 WORCESTER UNKNOWN 6849","telephone":"0231100146","email":null,"principal":"HG LOUW","quintile":"UNKNOWN","noFee":"NO","section21":"YES","urbanRural":"RURAL","learners":209,"educators":36,"longitude":19.4543386932,"latitude":-33.6337720467,"isSpecialNeeds":true},{"id":"130315610","emis":"130315610","name":"PIONIER-SKOOL","status":"OPEN","sector":"PUBLIC","type":"SPECIAL NEEDS EDUCATION CENTRE","phase":"SPECIAL NEEDS EDUCATION","specialisation":"UNKNOWN","district":"CAPE WINELANDS","circuit":"4","municipality":"BREEDE VALLEY","suburb":"WORCESTER","township":"Worcester Central","town":"WORCESTER","streetAddress":"ADDERLEYSTRAAT 20 WORCESTER 6850, WORCESTER, WORCESTER","postalAddress":"PRIVAATSAK X3048 WORCESTER UNKNOWN 6849","telephone":"0233422313","email":null,"principal":"M BREDENKAMP","quintile":"UNKNOWN","noFee":"NO","section21":"YES","urbanRural":"RURAL","learners":115,"educators":30,"longitude":19.4413558877,"latitude":-33.6432572811,"isSpecialNeeds":true},{"id":"130334626","emis":"130334626","name":"NUWE HOOP-SENTRUM","status":"OPEN","sector":"PUBLIC","type":"SPECIAL NEEDS EDUCATION CENTRE","phase":"SPECIAL NEEDS EDUCATION","specialisation":"UNKNOWN","district":"CAPE WINELANDS","circuit":"4","municipality":"BREEDE VALLEY","suburb":"PARKERSDAM","township":"Esselen Park","town":"WORCESTER","streetAddress":"LEIPOLDTLAAN 160 WORCESTER 6850, PARKERSDAM, WORCESTER","postalAddress":"PRIVAATSAK X3047 WORCESTER UNKNOWN 6849","telephone":"0230040076","email":null,"principal":"E HUMPHREYS","quintile":"UNKNOWN","noFee":"NO","section21":"YES","urbanRural":"RURAL","learners":346,"educators":35,"longitude":19.4523374694,"latitude":-33.6496248935,"isSpecialNeeds":true},{"id":"130334634","emis":"130334634","name":"EDEN SKOOL","status":"OPEN","sector":"PUBLIC","type":"SPECIAL NEEDS EDUCATION CENTRE","phase":"SPECIAL NEEDS EDUCATION","specialisation":"UNKNOWN","district":"CAPE WINELANDS","circuit":"4","municipality":"BREEDE VALLEY","suburb":"JOHNSONS PARK","township":"Johnsons Park","town":"WORCESTER","streetAddress":"FISHERSTRAAT HEXPARK WORCESTER 6850, JOHNSONS PARK, WORCESTER","postalAddress":"POSBUS 293 WORCESTER UNKNOWN 6850","telephone":"0233423770","email":null,"principal":"RUDOLPH JOHANNES","quintile":"UNKNOWN","noFee":"NO","section21":"YES","urbanRural":"URBAN","learners":188,"educators":13,"longitude":19.4634477958,"latitude":-33.6576674111,"isSpecialNeeds":true},{"id":"130447838","emis":"130447838","name":"BREEDE VALLEY SCHOOL OF SKILLS","status":"OPEN","sector":"PUBLIC","type":"SPECIAL NEEDS EDUCATION CENTRE","phase":"SCHOOL OF SKILLS","specialisation":"UNKNOWN","district":"CAPE WINELANDS","circuit":"4","municipality":"BREEDE VALLEY","suburb":"OUTSIDE A TOWN","township":"Breede Valley NU","town":"OUTSIDE A TOWN","streetAddress":"SLANGHOEKWEG RAWSONVILLE 6845, OUTSIDE A TOWN, OUTSIDE A TOWN","postalAddress":"PRIVAATSAK X1 RAWSONVILLE UNKNOWN 6845","telephone":"0233491807","email":null,"principal":"L SYCE","quintile":"UNKNOWN","noFee":"NO","section21":"YES","urbanRural":"RURAL","learners":257,"educators":20,"longitude":19.2699076446,"latitude":-33.6746016613,"isSpecialNeeds":true},{"id":"132324671","emis":"132324671","name":"RIEBEECK VALLEY SPECIAL SCHOOL","status":"OPEN","sector":"PUBLIC","type":"SPECIAL NEEDS EDUCATION CENTRE","phase":"SCHOOL OF SKILLS","specialisation":"UNKNOWN","district":"WEST COAST","circuit":"1","municipality":"SWARTLAND","suburb":"RIEBEEK WEST","township":"Riebeek-Wes SP","town":"RIEBEEK WEST","streetAddress":"ARKSTRAAT 9 RIEBEEK-WES 7306, RIEBEEK WEST, RIEBEEK WEST","postalAddress":"POSBUS 52 RIEBEEK-WES UNKNOWN 7306","telephone":"0224612241","email":null,"principal":"RJ RICKETT","quintile":"UNKNOWN","noFee":"NO","section21":"YES","urbanRural":"RURAL","learners":369,"educators":26,"longitude":18.8635566937,"latitude":-33.3513579276,"isSpecialNeeds":true},{"id":"132329746","emis":"132329746","name":"ROBINHILL SPECIAL SCHOOL","status":"OPEN","sector":"PUBLIC","type":"SPECIAL NEEDS EDUCATION CENTRE","phase":"SPECIAL NEEDS EDUCATION","specialisation":"UNKNOWN","district":"METRO NORTH","circuit":"10","municipality":"CITY OF CAPE TOWN","suburb":"BEACON HILL","township":"Beaconhill","town":"CITY OF CAPE TOWN","streetAddress":"H/V MONTREALRYLAAN EN SAMSONWEG 7352, BEACON HILL, CITY OF CAPE TOWN","postalAddress":"POSBUS 3119 REYGERSDAL ATLANTIS 7352","telephone":"0215724359","email":null,"principal":"J.B. COETZEE","quintile":"UNKNOWN","noFee":"NO","section21":"YES","urbanRural":"URBAN","learners":232,"educators":22,"longitude":18.506196277,"latitude":-33.563086806,"isSpecialNeeds":true},{"id":"132447897","emis":"132447897","name":"ATLANTIS VAARDIGHEIDSKOOL","status":"OPEN","sector":"PUBLIC","type":"SPECIAL NEEDS EDUCATION CENTRE","phase":"SCHOOL OF SKILLS","specialisation":"UNKNOWN","district":"METRO NORTH","circuit":"10","municipality":"CITY OF CAPE TOWN","suburb":"AVONDALE","township":"Avondale SP1","town":"CITY OF CAPE TOWN","streetAddress":"GOUDASTRAAT WESFLEUR ATLANTIS 7349, AVONDALE, CITY OF CAPE TOWN","postalAddress":"POST BOX 1403 DASSENBERG ATLANTIS 7350","telephone":"0215725022","email":null,"principal":"B CARLSE","quintile":"UNKNOWN","noFee":"NO","section21":"YES","urbanRural":"URBAN","learners":357,"educators":20,"longitude":18.482179132,"latitude":-33.5652547293,"isSpecialNeeds":true},{"id":"134302600","emis":"134302600","name":"WESKUS SPESIALE SKOOL","status":"OPEN","sector":"PUBLIC","type":"SPECIAL NEEDS EDUCATION CENTRE","phase":"SCHOOL OF SKILLS","specialisation":"UNKNOWN","district":"WEST COAST","circuit":"3","municipality":"SALDANHA BAY","suburb":"SALDANHA","township":"Saldanha SP","town":"SALDANHA","streetAddress":"SALDANHAWEG SALDANHA 7395, SALDANHA, SALDANHA","postalAddress":"PRIVAATSAK X6 SALDANHA UNKNOWN 7395","telephone":"0227141244","email":null,"principal":"C. KOEGLENBERG","quintile":"UNKNOWN","noFee":"NO","section21":"YES","urbanRural":"RURAL","learners":463,"educators":29,"longitude":17.9449741606,"latitude":-32.9920989151,"isSpecialNeeds":true},{"id":"134324663","emis":"134324663","name":"KARITAS SKOOL","status":"OPEN","sector":"PUBLIC","type":"SPECIAL NEEDS EDUCATION CENTRE","phase":"SPECIAL NEEDS EDUCATION","specialisation":"UNKNOWN","district":"WEST COAST","circuit":"3","municipality":"SALDANHA BAY","suburb":"LOUWVILLE","township":"Louwville","town":"VREDENBURG","streetAddress":"KOOITJIESKLOOFSTRAAT 20 LOUWVILLE 7380, LOUWVILLE, VREDENBURG","postalAddress":"POSBUS 1048 VREDENBURG UNKNOWN 7380","telephone":"0227151676","email":null,"principal":"A. ERASMUS","quintile":"UNKNOWN","noFee":"NO","section21":"YES","urbanRural":"RURAL","learners":190,"educators":21,"longitude":17.9980644051,"latitude":-32.9114950238,"isSpecialNeeds":true}]